memory_agent/__init__.py
memory_agent/memory.py
memory_agent/memory_agent.py
memory_agent/memory_checkpointer.py
memory_agent/memory_graph.py
memory_agent/memory_log.py
memory_agent/memory_persistence.py
memory_agent/memory_redis.py
memory_agent/state.py
memory_agent/kgrag/__init__.py
memory_agent/kgrag/kgrag_cache.py
memory_agent/kgrag/kgrag_components.py
memory_agent/kgrag/kgrag_prompt.py
memory_agent/kgrag/kgrag_utils.py
memory_agent/ollama/__init__.py
memory_agent/ollama/agent_ollama.py
memory_agent/ollama/kgrag_ollama.py
memory_agent/ollama/memory_ollama.py
memory_agent/openai/__init__.py
memory_agent/openai/agent_openai.py
memory_agent/openai/kgrag_openai.py
memory_agent/openai/memory_openai.py
memory_agent-3.0.3.dist-info/licenses/LICENSE.md
memory_agent-3.0.3.dist-info/METADATA
memory_agent-3.0.3.dist-info/WHEEL
memory_agent-3.0.3.dist-info/top_level.txt
memory_agent-3.0.3.dist-info/RECORD
